itolapi/__init__.py
itolapi/__version__.py
itolapi/comm.py
itolapi/itol.py
itolapi/itolexport.py
itolapi/py.typed
itolapi-4.1.5.dist-info/METADATA
itolapi-4.1.5.dist-info/WHEEL
itolapi-4.1.5.dist-info/entry_points.txt
itolapi-4.1.5.dist-info/top_level.txt
itolapi-4.1.5.dist-info/RECORD
