Metadata-Version: 2.1
Name: itolapi
Version: 4.1.5
Summary: API for interacting with itol.embl.de
Author-email: Albert Wang <git@albertyw.com>
License: MIT
Project-URL: Homepage, https://github.com/albertyw/itolapi
Keywords: tree,life,compbio,biology,bioinformatics
Classifier: Development Status :: 7 - Inactive
Classifier: Environment :: Console
Classifier: Intended Audience :: Developers
Classifier: Intended Audience :: Science/Research
Classifier: Natural Language :: English
Classifier: License :: OSI Approved :: MIT License
Classifier: Programming Language :: Python :: 3
Classifier: Programming Language :: Python :: 3.7
Classifier: Programming Language :: Python :: 3.8
Classifier: Programming Language :: Python :: 3.9
Classifier: Programming Language :: Python :: 3.10
Classifier: Programming Language :: Python :: 3.11
Classifier: Programming Language :: Python :: 3.12
Classifier: Topic :: Scientific/Engineering :: Bio-Informatics
Classifier: Typing :: Typed
Requires-Python: >=3.7
Requires-Dist: requests <3.0,>=2.0
Provides-Extra: test
Requires-Dist: coverage ==7.6.1 ; extra == 'test'
Requires-Dist: ruff ==0.6.2 ; extra == 'test'
Requires-Dist: mypy ==1.11.2 ; extra == 'test'
Requires-Dist: types-requests ==2.32.0.20240712 ; extra == 'test'
